seqspec/Assay.py
seqspec/File.py
seqspec/Read.py
seqspec/Region.py
seqspec/__init__.py
seqspec/main.py
seqspec/seqspec_check.py
seqspec/seqspec_diff.py
seqspec/seqspec_file.py
seqspec/seqspec_find.py
seqspec/seqspec_format.py
seqspec/seqspec_genbank.py
seqspec/seqspec_index.py
seqspec/seqspec_info.py
seqspec/seqspec_init.py
seqspec/seqspec_methods.py
seqspec/seqspec_modify.py
seqspec/seqspec_onlist.py
seqspec/seqspec_print.py
seqspec/seqspec_print_html.py
seqspec/seqspec_split.py
seqspec/seqspec_upgrade.py
seqspec/seqspec_version.py
seqspec/utils.py
seqspec/schema/seqspec.schema.json
seqspec-0.3.1.dist-info/LICENSE
seqspec-0.3.1.dist-info/METADATA
seqspec-0.3.1.dist-info/WHEEL
seqspec-0.3.1.dist-info/entry_points.txt
seqspec-0.3.1.dist-info/top_level.txt
seqspec-0.3.1.dist-info/RECORD
