Metadata-Version: 2.1
Name: seqspec
Version: 0.3.1
Home-page: https://github.com/sbooeshaghi/seqspec
Author: Sina Booeshaghi
Author-email: abooesha@caltech.edu
Maintainer: Sina Booeshaghi
Maintainer-email: abooesha@caltech.edu
License: MIT
Classifier: Environment :: Console
Classifier: Intended Audience :: Science/Research
Classifier: License :: OSI Approved :: MIT License
Classifier: Operating System :: OS Independent
Classifier: Programming Language :: Python :: 3.6
Classifier: Programming Language :: Python :: 3.7
Classifier: Programming Language :: Python :: 3.8
Classifier: Programming Language :: Python :: 3.9
Classifier: Programming Language :: Python :: 3.10
Classifier: Topic :: Scientific/Engineering :: Bio-Informatics
Classifier: Topic :: Utilities
Requires-Python: >=3.6
License-File: LICENSE
Requires-Dist: pyyaml>=6.0
Requires-Dist: jsonschema
Requires-Dist: newick
Requires-Dist: requests
Requires-Dist: biopython
Requires-Dist: packaging
